aiorobokassa/__init__.py
aiorobokassa/api/__init__.py
aiorobokassa/api/_protocols.py
aiorobokassa/api/base.py
aiorobokassa/api/invoice.py
aiorobokassa/api/payment.py
aiorobokassa/api/refund.py
aiorobokassa/client.py
aiorobokassa/constants.py
aiorobokassa/contrib/__init__.py
aiorobokassa/enums.py
aiorobokassa/exceptions.py
aiorobokassa/models/__init__.py
aiorobokassa/models/receipt.py
aiorobokassa/models/requests.py
aiorobokassa/utils/__init__.py
aiorobokassa/utils/helpers.py
aiorobokassa/utils/jwt.py
aiorobokassa/utils/signature.py
aiorobokassa/utils/xml.py
aiorobokassa-1.1.3.dist-info/METADATA
aiorobokassa-1.1.3.dist-info/WHEEL
aiorobokassa-1.1.3.dist-info/licenses/LICENSE
aiorobokassa-1.1.3.dist-info/RECORD
