Metadata-Version: 2.4
Name: aiorobokassa
Version: 1.1.3
Summary: Async Python library for RoboKassa payment gateway
License-Expression: MIT
License-File: LICENSE
Keywords: robokassa,payment,async,aiohttp
Author: Masa
Author-email: artness147@yandex.ru
Requires-Python: >=3.8
Classifier: Development Status :: 5 - Production/Stable
Classifier: Intended Audience :: Developers
Classifier: Programming Language :: Python :: 3
Classifier: Programming Language :: Python :: 3.8
Classifier: Programming Language :: Python :: 3.9
Classifier: Programming Language :: Python :: 3.10
Classifier: Programming Language :: Python :: 3.11
Classifier: Programming Language :: Python :: 3.12
Provides-Extra: dev
Provides-Extra: docs
Requires-Dist: aiohttp (>=3.8.0)
Requires-Dist: black (>=23.0.0) ; extra == "dev"
Requires-Dist: furo (>=2023.0.0) ; extra == "docs"
Requires-Dist: mypy (>=1.0.0) ; extra == "dev"
Requires-Dist: pydantic (>=2.0.0)
Requires-Dist: pytest (>=7.0.0) ; extra == "dev"
Requires-Dist: pytest-asyncio (>=0.21.0) ; extra == "dev"
Requires-Dist: pytest-cov (>=4.0.0) ; extra == "dev"
Requires-Dist: ruff (>=0.1.0) ; extra == "dev"
Requires-Dist: sphinx (>=7.0.0) ; extra == "docs"
Requires-Dist: sphinx-autodoc-typehints (>=1.24.0) ; extra == "docs"
Requires-Dist: types-aiofiles (>=23.0.0) ; extra == "dev"
Project-URL: Bug Reports, https://github.com/masasibata/aiorobokassa/issues
Project-URL: Documentation, https://aiorobokassa.readthedocs.io
Project-URL: Homepage, https://github.com/masasibata/aiorobokassa
Project-URL: Repository, https://github.com/masasibata/aiorobokassa
